torque_drag/__init__.py
torque_drag/main.py
torque_drag/plot.py
torque_drag-0.1.1.dist-info/LICENSE.md
torque_drag-0.1.1.dist-info/METADATA
torque_drag-0.1.1.dist-info/WHEEL
torque_drag-0.1.1.dist-info/top_level.txt
torque_drag-0.1.1.dist-info/RECORD
