Metadata-Version: 2.1
Name: torque-drag
Version: 0.1.1
Summary: Torque and Drag Calculation
Home-page: https://github.com/pro-well-plan/torque_drag
Author: Pro Well Plan AS
Author-email: juan@prowellplan.com
License: LGPL v3
Keywords: drilling
Platform: UNKNOWN
Classifier: Programming Language :: Python :: 3
Classifier: License :: OSI Approved :: GNU Lesser General Public License v3 (LGPLv3)
Classifier: Natural Language :: English
Classifier: Topic :: Scientific/Engineering
Classifier: Topic :: Software Development
Classifier: Topic :: Software Development :: Libraries
Classifier: Topic :: Utilities
Requires-Dist: plotly
